{
	"class" : {
		"title:" : "ek 4/12/2017 16:12" },
	"instance" : {
		"accept:" : "TB 5/5/2017 11:32",
		"cancel:" : "TB 5/5/2017 11:32",
		"colorMode" : "lcj 5/12/2017 11:53",
		"content:" : "ek 4/12/2017 16:12",
		"handlesMouseDown:" : "lcj 5/12/2017 11:53",
		"initialize" : "TB 4/7/2018 08:54",
		"openCentered" : "lcj 5/15/2017 11:32",
		"openFor:" : "lcj 5/15/2017 11:30",
		"parentTopLevel" : "lcj 5/12/2017 11:03",
		"parentTopLevel:" : "lcj 5/12/2017 11:03",
		"shown" : "lcj 5/15/2017 11:32",
		"title" : "TB 5/10/2017 15:19",
		"title:" : "al 4/27/2017 12:34",
		"topLevel" : "lcj 5/12/2017 11:53" } }
